robotframework_zebrunner/__init__.py
robotframework_zebrunner/api/__init__.py
robotframework_zebrunner/api/client.py
robotframework_zebrunner/api/models.py
robotframework_zebrunner/ci_loaders.py
robotframework_zebrunner/context.py
robotframework_zebrunner/errors.py
robotframework_zebrunner/library.py
robotframework_zebrunner/listener.py
robotframework_zebrunner/logs.py
robotframework_zebrunner/selenium_integration.py
robotframework_zebrunner/settings.py
robotframework_zebrunner/tcm/__init__.py
robotframework_zebrunner/tcm/base.py
robotframework_zebrunner/tcm/test_rail.py
robotframework_zebrunner/tcm/xray.py
robotframework_zebrunner/tcm/zephyr.py
robotframework_zebrunner/utils.py
robotframework_zebrunner-0.3.2.dist-info/LICENSE
robotframework_zebrunner-0.3.2.dist-info/WHEEL
robotframework_zebrunner-0.3.2.dist-info/METADATA
robotframework_zebrunner-0.3.2.dist-info/RECORD
