Metadata-Version: 2.1
Name: robotframework-zebrunner
Version: 0.3.2
Summary: Robotframework connector for Zebrunner reporting
Home-page: https://zebrunner.com/documentation/agents/robot
License: Apache
Keywords: automation,zebrunner,testing
Author: Anatoliy Platonov
Author-email: platonoff.dev@gmail.com
Requires-Python: >=3.7
Classifier: Development Status :: 5 - Production/Stable
Classifier: Intended Audience :: Developers
Classifier: Intended Audience :: Information Technology
Classifier: Intended Audience :: System Administrators
Classifier: License :: OSI Approved :: Apache Software License
Classifier: License :: Other/Proprietary License
Classifier: Operating System :: OS Independent
Classifier: Programming Language :: Python :: 3
Classifier: Programming Language :: Python :: 3.7
Classifier: Programming Language :: Python :: 3.8
Classifier: Programming Language :: Python :: 3.9
Classifier: Programming Language :: Python :: 3.10
Classifier: Programming Language :: Python :: 3.11
Classifier: Programming Language :: Python :: 3
Classifier: Programming Language :: Python :: 3.7
Classifier: Programming Language :: Python :: 3.8
Classifier: Programming Language :: Python :: 3.9
Classifier: Topic :: Internet
Classifier: Topic :: Software Development
Classifier: Topic :: Software Development :: Libraries
Classifier: Topic :: Software Development :: Libraries :: Application Frameworks
Classifier: Topic :: Software Development :: Libraries :: Python Modules
Requires-Dist: PyYAML (>=5.3.1,<6.0.0)
Requires-Dist: httpx (>=0.22.0,<0.23.0)
Requires-Dist: pydantic (>=1.0)
Requires-Dist: python-dotenv (>=0.10)
Requires-Dist: robotframework (>=3.2.2)
Requires-Dist: robotframework-seleniumlibrary (>=4.0.0)
Project-URL: Repository, https://github.com/zebrunner/python-agent-robot
